README
setup.py
biocma/__init__.py
biocma/biocma.py
biocma/cma.py
biocma/sugar.py
biocma/utils.py
biocma.egg-info/PKG-INFO
biocma.egg-info/SOURCES.txt
biocma.egg-info/dependency_links.txt
biocma.egg-info/top_level.txt
test/test_all.py