Metadata-Version: 1.1
Name: biocma
Version: 0.2.1
Summary: I/O and utilities for the Consensus Multiple Alignment (CMA) file format.
Home-page: http://github.com/etal/biocma
Author: Eric Talevich
Author-email: eric.talevich@gmail.com
License: UNKNOWN
Platform: UNKNOWN
Classifier: Development Status :: 4 - Beta
Classifier: Intended Audience :: Science/Research
Classifier: License :: OSI Approved :: BSD License
Classifier: Programming Language :: Python :: 2.7
Classifier: Programming Language :: Python :: Implementation :: PyPy
Classifier: Topic :: Scientific/Engineering :: Bio-Informatics
